csemod/__init__.py
csemod/content.py
csemod/main.py
csemod-0.0.4.dist-info/METADATA
csemod-0.0.4.dist-info/WHEEL
csemod-0.0.4.dist-info/top_level.txt
csemod-0.0.4.dist-info/RECORD
